django_entity_rbac/__init__.py
django_entity_rbac/constants.py
django_entity_rbac/exceptions.py
django_entity_rbac/models.py
django_entity_rbac-0.1.0.dist-info/WHEEL
django_entity_rbac-0.1.0.dist-info/METADATA
django_entity_rbac-0.1.0.dist-info/RECORD
